piped_zmq
