Metadata-Version: 1.0
Name: piped.contrib.zmq
Version: 0.4.0
Summary: ZeroMQ processors and providers for Piped.
Home-page: http://piped.io
Author: Piped Project Contributors
Author-email: piped@librelist.com
License: MIT
Platform: UNKNOWN
Classifier: Development Status :: 4 - Beta
Classifier: Environment :: Plugins
Classifier: Framework :: Twisted
Classifier: Operating System :: OS Independent
Classifier: Topic :: Communications
